codation/__init__.py
codation-0.0.1.dist-info/LICENSE
codation-0.0.1.dist-info/METADATA
codation-0.0.1.dist-info/WHEEL
codation-0.0.1.dist-info/top_level.txt
codation-0.0.1.dist-info/RECORD
