Metadata-Version: 2.1
Name: codation
Version: 0.0.1
Summary: A jinja2 framework for project templating
Author-email: Victor Mattos <5757883+vicmattos@users.noreply.github.com>
Project-URL: Homepage, https://github.com/vicmattos/codation
Project-URL: Issues, https://github.com/vicmattos/codation/issues
Classifier: Programming Language :: Python :: 3
Classifier: License :: OSI Approved :: MIT License
Classifier: Operating System :: OS Independent
License-File: LICENSE
